skola24lunch/__init__.py
skola24lunch/parser.py
skola24lunch-0.0.1.dist-info/LICENSE
skola24lunch-0.0.1.dist-info/METADATA
skola24lunch-0.0.1.dist-info/WHEEL
skola24lunch-0.0.1.dist-info/top_level.txt
skola24lunch-0.0.1.dist-info/RECORD
