Metadata-Version: 2.1
Name: skola24lunch
Version: 0.0.1
Summary: Library to handle Skola24's obscure API
Home-page: https://github.com/donran/skola24lunch
Author: Pontus Norrström
Author-email: donran@protonmail.com
License: UNKNOWN
Platform: UNKNOWN
Classifier: Programming Language :: Python :: 3
Classifier: License :: OSI Approved :: GNU General Public License v3 (GPLv3)
Classifier: Operating System :: OS Independent
Requires-Python: >=3.6
